[
    {
        "id":"98123748JQSFhhuaze987",
        "startFrom":"The Pale",
        "goTo":"Velpeau",
        "startTime":"2021-09-28T23:30",
        "hostID": "I8938R775J873587Ddqsdk"
    },

    {
        "id":"777349834jqskd4884",
        "startFrom":"The Pale",
        "goTo":"Prébende",
        "startTime":"2021-09-28T23:45",
        "hostID": "8827387283SJJazeaze"
    },

    {
        "id":"8348975874589NNndqsd734",
        "startFrom":"Le Kubrik",
        "goTo":"Velpeau",
        "startTime":"2021-10-01T22:30",
        "hostID": "8873748°jfjq3785785"
    },

    {
        "id":"98123748JQSFhhuaze987",
        "startFrom":"Place de la Victoire",
        "goTo":"Place de la Liberté",
        "startTime":"2021-10-02T01:30",
        "hostID": "I8938R775J873587Ddqsdk"
    },

    {
        "id":"98123748JQSFhhuaze987",
        "startFrom":"Jean-Jaurès",
        "goTo":"Velpeau",
        "startTime":"2021-09-30T02:30",
        "hostID": "I8938R775J873587Ddqsdk"
    }
]